engagespot/__init__.py
engagespot/client.py
tests/__init__.py
tests/manual.py
engagespot-1.1.0.dist-info/LICENCE
engagespot-1.1.0.dist-info/METADATA
engagespot-1.1.0.dist-info/WHEEL
engagespot-1.1.0.dist-info/top_level.txt
engagespot-1.1.0.dist-info/RECORD
