Metadata-Version: 2.1
Name: engagespot
Version: 1.1.0
Summary: Python library for communicating with Engagespot REST API.
Home-page: https://github.com/Engagespot/engagespot-python
Author: Anand
Classifier: Programming Language :: Python :: 3
Classifier: License :: OSI Approved :: MIT License
Classifier: Operating System :: OS Independent
Requires-Python: >=3.6
License-File: LICENCE
Requires-Dist: requests >=2.23.0
